version_hunter/__init__.py
version_hunter/versioner.py
version_hunter-1.0.dist-info/DESCRIPTION.rst
version_hunter-1.0.dist-info/METADATA
version_hunter-1.0.dist-info/RECORD
version_hunter-1.0.dist-info/WHEEL
version_hunter-1.0.dist-info/metadata.json
version_hunter-1.0.dist-info/top_level.txt
