Metadata-Version: 2.0
Name: version-hunter
Version: 1.0
Summary: Command line versioning helper for Cx_Freeze / Inno Setup builds.
Home-page: https://github.com/Tomasz-Kluczkowski/versioner
Author: Tomasz Kluczkowski
Author-email: tomaszk1@hotmail.co.uk
License: MIT
Platform: UNKNOWN
